MANIFEST.in
README.md
requirements.txt
setup.cfg
setup.py
GreenLearning.egg-info/PKG-INFO
GreenLearning.egg-info/SOURCES.txt
GreenLearning.egg-info/dependency_links.txt
GreenLearning.egg-info/requires.txt
GreenLearning.egg-info/top_level.txt
greenlearning/__init__.py
greenlearning/activations.py
greenlearning/loss_function.py
greenlearning/matrix_networks.py
greenlearning/model.py
greenlearning/neural_network.py
greenlearning/quadrature_weights.py
greenlearning/utils/__init__.py
greenlearning/utils/backend.py
greenlearning/utils/config.py
greenlearning/utils/external_optimizer.py
greenlearning/utils/load_data.py
greenlearning/utils/plotting.py
greenlearning/utils/print_weights.py
greenlearning/utils/real.py
greenlearning/utils/save_results.py
greenlearning/utils/tf_session.py
greenlearning/utils/visualization.py