Metadata-Version: 2.1
Name: GreenLearning
Version: 1.0
Summary: Deep learning library for learning Green's functions
Home-page: https://github.com/NBoulle/greenlearning
Author: Nicolas Boulle
Author-email: boulle@maths.ox.ac.uk
License: Apache-2.0
Download-URL: https://github.com/NBoulle/greenlearning/tarball/v1.0
Keywords: Deep Learning,Machine Learning,Neural Networks,Scientific computing,Green's functions,PDE learning
Platform: UNKNOWN
Classifier: Development Status :: 4 - Beta
Classifier: Intended Audience :: Developers
Classifier: Intended Audience :: Education
Classifier: Intended Audience :: Science/Research
Classifier: License :: OSI Approved :: Apache Software License
Classifier: Programming Language :: Python :: 3
Classifier: Programming Language :: Python :: 3.6
Classifier: Programming Language :: Python :: 3.7
Classifier: Programming Language :: Python :: 3.8
Classifier: Topic :: Scientific/Engineering
Classifier: Topic :: Scientific/Engineering :: Artificial Intelligence
Classifier: Topic :: Scientific/Engineering :: Mathematics
Classifier: Topic :: Scientific/Engineering :: Physics
Classifier: Topic :: Software Development :: Libraries
Classifier: Topic :: Software Development :: Libraries :: Python Modules
